revlib/__init__.py
revlib/core.py
revlib/utils.py
revlib-1.7.2.dist-info/LICENSE
revlib-1.7.2.dist-info/METADATA
revlib-1.7.2.dist-info/WHEEL
revlib-1.7.2.dist-info/top_level.txt
revlib-1.7.2.dist-info/RECORD
