Metadata-Version: 2.1
Name: revlib
Version: 1.7.2
Summary: Simple and efficient RevNet-Library for PyTorch with XLA and DeepSpeed support and parameter offload
Home-page: https://github.com/clashluke/revlib
Author: Lucas Nestler
Author-email: github.revlib@nestler.sh
License: BSD
Platform: UNKNOWN
Classifier: Development Status :: 5 - Production/Stable
Classifier: License :: OSI Approved :: BSD License
Classifier: Programming Language :: Python
Classifier: Programming Language :: Python :: 3.7
Classifier: Programming Language :: Python :: 3.8
Classifier: Programming Language :: Python :: 3.9
Classifier: Topic :: Software Development :: Libraries
Classifier: Topic :: Software Development :: Libraries :: Python Modules
Classifier: Intended Audience :: Developers
Requires-Python: >=3.7
License-File: LICENSE
